duda_dummy/__init__.py
duda_dummy-0.0.2.dist-info/LICENSE
duda_dummy-0.0.2.dist-info/METADATA
duda_dummy-0.0.2.dist-info/WHEEL
duda_dummy-0.0.2.dist-info/top_level.txt
duda_dummy-0.0.2.dist-info/RECORD
